fluxfootprints/__init__.py
fluxfootprints/by_row_fetch_tools.py
fluxfootprints/ffp_daily_monthly_helper.py
fluxfootprints/ffp_xr.py
fluxfootprints/improved_ffp.py
fluxfootprints/kormannmeixner.py
fluxfootprints/ls_footprint_model.py
fluxfootprints/new_ffp.py
fluxfootprints/nldas_download_tools.py
fluxfootprints/wang_footprint.py
fluxfootprints-0.2.4.dist-info/licenses/LICENSE
fluxfootprints-0.2.4.dist-info/METADATA
fluxfootprints-0.2.4.dist-info/WHEEL
fluxfootprints-0.2.4.dist-info/top_level.txt
fluxfootprints-0.2.4.dist-info/RECORD
