Metadata-Version: 2.4
Name: fluxfootprints
Version: 0.2.4
Summary: A comprehensive Python package for micrometeorological footprint analysis
Author-email: Paul Inkenbrandt <paulinkenbrandt@utah.gov>, Natascha Kljun <natascha.kljun@cec.lu.se>, John Volk <John.Volk@dri.edu>
License: GNU General Public License v3.0
Project-URL: Homepage, https://github.com/inkenbrandt/fluxfootprints
Project-URL: Documentation, https://fluxfootprints.readthedocs.io/en/stable/
Requires-Python: >=3.10
License-File: LICENSE
Requires-Dist: numpy>=1.24
Requires-Dist: pandas>=1.5
Requires-Dist: xarray>=2023.1.0
Requires-Dist: scipy>=1.9
Requires-Dist: matplotlib>=3.6
Requires-Dist: shapely>=2.0
Requires-Dist: fiona>=1.9
Requires-Dist: geopandas>=0.14
Requires-Dist: rasterio>=1.3
Requires-Dist: pyproj>=3.5
Requires-Dist: affine>=2.4
Requires-Dist: requests>=2.28
Requires-Dist: netcdf4>=1.6
Requires-Dist: refet>=0.4
Provides-Extra: docs
Requires-Dist: sphinx>=7.0; extra == "docs"
Requires-Dist: sphinx-rtd-theme>=1.2; extra == "docs"
Requires-Dist: myst-parser>=2.0; extra == "docs"
Requires-Dist: sphinxcontrib-bibtex>=2.5; extra == "docs"
Requires-Dist: sphinx-copybutton>=0.5; extra == "docs"
Requires-Dist: sphinx-autodoc-typehints>=1.20; extra == "docs"
Requires-Dist: sphinx-gallery>=0.14; extra == "docs"
Requires-Dist: nbsphinx>=0.9; extra == "docs"
Requires-Dist: nbsphinx-link>=1.4; extra == "docs"
Requires-Dist: numpydoc>=1.1; extra == "docs"
Provides-Extra: examples
Requires-Dist: jupyter>=1.0; extra == "examples"
Requires-Dist: ipykernel>=6.0; extra == "examples"
Requires-Dist: matplotlib>=3.6; extra == "examples"
Requires-Dist: seaborn>=0.12; extra == "examples"
Requires-Dist: plotly>=5.15; extra == "examples"
Provides-Extra: test
Requires-Dist: pytest>=7.0; extra == "test"
Requires-Dist: pytest-cov>=4.0; extra == "test"
Requires-Dist: tox>=4.0; extra == "test"
Requires-Dist: black>=23.0; extra == "test"
Requires-Dist: ruff>=0.1; extra == "test"
Dynamic: license-file
